utils
galah
