Metadata-Version: 1.0
Name: galah
Version: 0.1.3
Summary: Galah is a utility to allow better professer student communication
Home-page: UNKNOWN
Author: John Sullivan
Author-email: jsull003@ucr.edu
License: AGPLv3
Platform: UNKNOWN
